boto3/__init__.py
boto3/compat.py
boto3/exceptions.py
boto3/session.py
boto3/utils.py
boto3/data/s3/2006-03-01/resources-1.json
boto3/docs/__init__.py
boto3/docs/action.py
boto3/docs/attr.py
boto3/docs/base.py
boto3/docs/client.py
boto3/docs/collection.py
boto3/docs/docstring.py
boto3/docs/method.py
boto3/docs/resource.py
boto3/docs/service.py
boto3/docs/subresource.py
boto3/docs/utils.py
boto3/docs/waiter.py
boto3/resources/__init__.py
boto3/resources/action.py
boto3/resources/base.py
boto3/resources/collection.py
boto3/resources/factory.py
boto3/resources/model.py
boto3/resources/params.py
boto3/resources/response.py
boto3/s3/__init__.py
boto3/s3/inject.py
boto3/s3/transfer.py
ibm_cos_sdk-1.2.0.dist-info/DESCRIPTION.rst
ibm_cos_sdk-1.2.0.dist-info/METADATA
ibm_cos_sdk-1.2.0.dist-info/metadata.json
ibm_cos_sdk-1.2.0.dist-info/RECORD
ibm_cos_sdk-1.2.0.dist-info/top_level.txt
ibm_cos_sdk-1.2.0.dist-info/WHEEL
