Metadata-Version: 2.0
Name: ibm-cos-sdk
Version: 1.2.0
Summary: IBM SDK for Python
Home-page: https://github.com/ibm/ibm-cos-sdk-python
Author: IBM
Author-email: UNKNOWN
License: Apache License 2.0
Platform: UNKNOWN
Classifier: Development Status :: 5 - Production/Stable
Classifier: Intended Audience :: Developers
Classifier: Natural Language :: English
Classifier: License :: OSI Approved :: Apache Software License
Classifier: Programming Language :: Python
Classifier: Programming Language :: Python :: 2.6
Classifier: Programming Language :: Python :: 2.7
Classifier: Programming Language :: Python :: 3
Classifier: Programming Language :: Python :: 3.3
Classifier: Programming Language :: Python :: 3.4
Classifier: Programming Language :: Python :: 3.5
Classifier: Programming Language :: Python :: 3.6
Requires-Dist: ibm-cos-sdk-core>=1.0.0,==1.*
Requires-Dist: ibm-cos-sdk-s3transfer>=1.0.0,==1.*
